{
	"info": {
		"_postman_id": "3c6935ac-e5b0-4945-8c8a-a0c6b4fa6580",
		"name": "Task Management",
		"schema": "https://schema.getpostman.com/json/collection/v2.1.0/collection.json"
	},
	"item": [
		{
			"name": "user",
			"item": [
				{
					"name": "Register",
					"request": {
						"method": "POST",
						"header": [],
						"body": {
							"mode": "raw",
							"raw": "{\r\n    \"name\":\"soso\",\r\n    \"password\":\"123456\",\r\n    \"type\":\"tstuser\",\r\n    \"email\":\"soo@gm.com\"\r\n}",
							"options": {
								"raw": {
									"language": "json"
								}
							}
						},
						"url": {
							"raw": "http://localhost:3000/user/register",
							"protocol": "http",
							"host": [
								"localhost"
							],
							"port": "3000",
							"path": [
								"user",
								"register"
							]
						}
					},
					"response": []
				},
				{
					"name": "login",
					"request": {
						"method": "POST",
						"header": [],
						"body": {
							"mode": "raw",
							"raw": "{\r\n    \"email\": \"soo@gm.com\",\r\n    \"password\": \"123456\"\r\n}"
						},
						"url": {
							"raw": "http://localhost:3000/user/login",
							"protocol": "http",
							"host": [
								"localhost"
							],
							"port": "3000",
							"path": [
								"user",
								"login"
							]
						}
					},
					"response": []
				}
			]
		},
		{
			"name": "tasks",
			"item": []
		},
		{
			"name": "reports",
			"item": []
		}
	]
}